mkdata/__init__.py
mkdata/_base.py
mkdata/_env.py
mkdata/_utils.py
mkdata/cli.py
mkdata/code_block.py
mkdata/execute.py
mkdata/interpreter.py
mkdata/parser.py
mkdata/preimport.py
mkdata/sentence.py
mkdata/syntax.py
mkdata-1.2.0.dist-info/licenses/LICENSE
mkdata-1.2.0.dist-info/METADATA
mkdata-1.2.0.dist-info/WHEEL
mkdata-1.2.0.dist-info/entry_points.txt
mkdata-1.2.0.dist-info/top_level.txt
mkdata-1.2.0.dist-info/RECORD
