Metadata-Version: 2.4
Name: mkdata
Version: 1.2.0
Summary: Simple but powerful batch data generator based on Python.
Author-email: RayZh <rayzhangshanghai@hotmail.com>
Maintainer-email: RayZh <rayzhangshanghai@hotmail.com>, rogerflowey <rogerwangabc@163.com>
License-Expression: MIT
Project-URL: Homepage, https://github.com/RayZh-hs/mkdata
Classifier: Programming Language :: Python :: 3
Classifier: Operating System :: OS Independent
Requires-Python: >=3.8
License-File: LICENSE
Dynamic: license-file
